MANIFEST.in
README.rst
setup.py
advertising/admin.py
advertising/models.py
advertising/validators.py
advertising/version.py
advertising/static/advertising/js/events.js
advertising/templatetags/__init__.py
advertising/templatetags/image.py
django_advertising.egg-info/PKG-INFO
django_advertising.egg-info/SOURCES.txt
django_advertising.egg-info/dependency_links.txt
django_advertising.egg-info/not-zip-safe
django_advertising.egg-info/top_level.txt