Metadata-Version: 1.1
Name: django-advertising
Version: 0.0.5
Summary: Django application for show advertising configurable.
Home-page: https://github.com/mapeveri/django-advertising
Author: Peveri Martin
Author-email: martinpeveri@gmail.com
License: BSD License
Platform: UNKNOWN
Classifier: Environment :: Web Environment
Classifier: Framework :: Django
Classifier: Intended Audience :: Developers
Classifier: License :: OSI Approved :: BSD License
Classifier: Operating System :: OS Independent
Classifier: Programming Language :: Python
Classifier: Topic :: Internet :: WWW/HTTP
Classifier: Topic :: Internet :: WWW/HTTP :: Dynamic Content
